{"chunk":0,"numChunks":2,"fileHash":"er5v4SXhLeR9n7O/BsfT6pZNtYWfLEbqTlbm3A4W09Q=","filePath":"web/admin/src/components/form/Select.vue","content":"<template>\n  <div>\n    <label :for=\"id\" :class=\"error ? 'border-red-500' : ''\">\n      <Field v-slot=\"{ value }\" v-model=\"model\" as=\"select\" :name=\"id\" :id=\"id\" :rules=\"rules\" class=\"form-select field peer\">\n        <option value=\"\" disabled>Please select</option>\n        <option v-for=\"option in options\" :key=\"option\" :value=\"option\" :selected=\"value && value.includes(option)\">\n          {{ option }}\n        </option>\n      </Field>\n\n      <span class=\"title\">{{ title }}</span>\n      <span class=\"ico\" v-if=\"ico\">\n        <SvgIcon :name=\"ico\" stroke=\"currentColor\" class=\"h-5 w-5\" :class=\"error ? 'text-red-500' : 'text-gray-400'\" />\n      </span>\n    </label>\n    <span class=\"error\" v-if=\"error\">{{ error }}</span>\n  </div>\n</template>\n\n<script setup>\nimport { computed } from \"vue\";\nimport { Field } from \"vee-validate\";\n\nconst props = defineProps({\n  modelValue: {\n    type: String,\n    default: \"\",\n    required: true,\n  },\n  id: {\n    type: String,\n    default: \"name\",\n  },\n  title: {\n    type: String,\n    default: \"Name\",\n  },\n  options: {\n    type: Object,\n    required: true,\n  },\n  rules: {\n    type: String,\n    default: \"\",\n  },\n  color: {\n    type: String,\n    default: \"indigo\",\n  },\n  ico: String,\n  error: String,\n});\n\nconst emits = defineEmits([\"update:modelValue\"]);\nconst model = computed({\n  get: () => {\n    return props.modelValue;\n  },\n  set: (val) => {\n"}